lims/.config.ini
lims/__init__.py
lims/banner.txt
lims/version.json
lims/bin/__init__.py
lims/bin/lims-main.py
lims/bin/main.py
lims/tools/__init__.py
lims/tools/check.py
lims/tools/login.py
lims/tools/project.py
lims/tools/release.py
lims/tools/report.py
lims/tools/sample.py
lims/tools/utils.py
lims-1.0.2.dist-info/METADATA
lims-1.0.2.dist-info/WHEEL
lims-1.0.2.dist-info/entry_points.txt
lims-1.0.2.dist-info/top_level.txt
lims-1.0.2.dist-info/RECORD
