Metadata-Version: 2.1
Name: lims
Version: 1.0.2
Summary: toolkits for lims
Home-page: https://github.com/suqingdong/lims
Author: suqingdong
Author-email: suqingdong@novogene.com
License: BSD License
Platform: UNKNOWN
Classifier: Development Status :: 5 - Production/Stable
Classifier: Operating System :: OS Independent
Classifier: Intended Audience :: Developers
Classifier: License :: OSI Approved :: BSD License
Classifier: Programming Language :: Python
Classifier: Programming Language :: Python :: Implementation
Classifier: Programming Language :: Python :: 3
Classifier: Topic :: Software Development :: Libraries
Requires-Dist: bs4
Requires-Dist: requests
Requires-Dist: python-dateutil
